.coveragerc
.mailmap
.testr.conf
AUTHORS
CONTRIBUTING.rst
ChangeLog
HACKING.rst
LICENSE
MANIFEST.in
README.rst
babel.cfg
requirements.txt
setup.cfg
setup.py
test-requirements.txt
tox.ini
doc/source/conf.py
doc/source/contributing.rst
doc/source/index.rst
doc/source/installation.rst
doc/source/readme.rst
doc/source/usage.rst
helionsdk/__init__.py
helionsdk/hp.py
helionsdk/shell.py
helionsdk.egg-info/PKG-INFO
helionsdk.egg-info/SOURCES.txt
helionsdk.egg-info/dependency_links.txt
helionsdk.egg-info/entry_points.txt
helionsdk.egg-info/not-zip-safe
helionsdk.egg-info/pbr.json
helionsdk.egg-info/requires.txt
helionsdk.egg-info/test-requires.txt
helionsdk.egg-info/top_level.txt
helionsdk/dns/__init__.py
helionsdk/dns/dns_service.py
helionsdk/dns/version.py
helionsdk/dns/v1/__init__.py
helionsdk/dns/v1/_proxy.py
helionsdk/dns/v1/domain.py
helionsdk/tests/__init__.py
helionsdk/tests/functional/__init__.py
helionsdk/tests/functional/base.py
helionsdk/tests/functional/dns/__init__.py
helionsdk/tests/functional/dns/v1/__init__.py
helionsdk/tests/functional/dns/v1/test_domain.py
helionsdk/tests/unit/__init__.py
helionsdk/tests/unit/test_hp.py
helionsdk/tests/unit/dns/__init__.py
helionsdk/tests/unit/dns/test_dns_service.py
helionsdk/tests/unit/dns/test_version.py
helionsdk/tests/unit/dns/v1/__init__.py
helionsdk/tests/unit/dns/v1/test_domain.py
helionsdk/tests/unit/dns/v1/test_proxy.py